<annotation>
  <path>dataset\images\train\000000457074.jpg</path><folder>JPEG</folder>
  <filename>000000457074.jpg</filename>
  <size>
    <width>500</width>
    <height>346</height>
    <depth>3</depth>
  </size>
  <object>
    <name>person</name>
    <difficult>0</difficult>
    <bndbox>
      <xmin>223</xmin>
      <ymin>190</ymin>
      <xmax>261</xmax>
      <ymax>346</ymax>
    </bndbox>
  </object>
  <object>
    <name>person</name>
    <difficult>0</difficult>
    <bndbox>
      <xmin>192</xmin>
      <ymin>204</ymin>
      <xmax>211</xmax>
      <ymax>268</ymax>
    </bndbox>
  </object>
  <object>
    <name>person</name>
    <difficult>0</difficult>
    <bndbox>
      <xmin>18</xmin>
      <ymin>181</ymin>
      <xmax>93</xmax>
      <ymax>343</ymax>
    </bndbox>
  </object>
</annotation>
