<annotation>
  <path>dataset\images\train\000000561186.jpg</path><folder>JPEG</folder>
  <filename>000000561186.jpg</filename>
  <size>
    <width>500</width>
    <height>176</height>
    <depth>3</depth>
  </size>
  <object>
    <name>car</name>
    <difficult>0</difficult>
    <bndbox>
      <xmin>276</xmin>
      <ymin>73</ymin>
      <xmax>295</xmax>
      <ymax>88</ymax>
    </bndbox>
  </object>
  <object>
    <name>motorcycle</name>
    <difficult>0</difficult>
    <bndbox>
      <xmin>35</xmin>
      <ymin>113</ymin>
      <xmax>126</xmax>
      <ymax>176</ymax>
    </bndbox>
  </object>
  <object>
    <name>motorcycle</name>
    <difficult>0</difficult>
    <bndbox>
      <xmin>156</xmin>
      <ymin>102</ymin>
      <xmax>204</xmax>
      <ymax>159</ymax>
    </bndbox>
  </object>
  <object>
    <name>person</name>
    <difficult>0</difficult>
    <bndbox>
      <xmin>163</xmin>
      <ymin>84</ymin>
      <xmax>194</xmax>
      <ymax>146</ymax>
    </bndbox>
  </object>
  <object>
    <name>person</name>
    <difficult>0</difficult>
    <bndbox>
      <xmin>57</xmin>
      <ymin>94</ymin>
      <xmax>107</xmax>
      <ymax>174</ymax>
    </bndbox>
  </object>
  <object>
    <name>person</name>
    <difficult>0</difficult>
    <bndbox>
      <xmin>97</xmin>
      <ymin>96</ymin>
      <xmax>121</xmax>
      <ymax>165</ymax>
    </bndbox>
  </object>
  <object>
    <name>motorcycle</name>
    <difficult>0</difficult>
    <bndbox>
      <xmin>242</xmin>
      <ymin>80</ymin>
      <xmax>256</xmax>
      <ymax>99</ymax>
    </bndbox>
  </object>
  <object>
    <name>person</name>
    <difficult>0</difficult>
    <bndbox>
      <xmin>242</xmin>
      <ymin>73</ymin>
      <xmax>254</xmax>
      <ymax>95</ymax>
    </bndbox>
  </object>
  <object>
    <name>person</name>
    <difficult>0</difficult>
    <bndbox>
      <xmin>344</xmin>
      <ymin>103</ymin>
      <xmax>393</xmax>
      <ymax>143</ymax>
    </bndbox>
  </object>
  <object>
    <name>person</name>
    <difficult>0</difficult>
    <bndbox>
      <xmin>434</xmin>
      <ymin>107</ymin>
      <xmax>482</xmax>
      <ymax>146</ymax>
    </bndbox>
  </object>
  <object>
    <name>person</name>
    <difficult>0</difficult>
    <bndbox>
      <xmin>475</xmin>
      <ymin>82</ymin>
      <xmax>496</xmax>
      <ymax>134</ymax>
    </bndbox>
  </object>
  <object>
    <name>person</name>
    <difficult>0</difficult>
    <bndbox>
      <xmin>94</xmin>
      <ymin>89</ymin>
      <xmax>103</xmax>
      <ymax>108</ymax>
    </bndbox>
  </object>
  <object>
    <name>person</name>
    <difficult>0</difficult>
    <bndbox>
      <xmin>72</xmin>
      <ymin>82</ymin>
      <xmax>83</xmax>
      <ymax>114</ymax>
    </bndbox>
  </object>
  <object>
    <name>person</name>
    <difficult>0</difficult>
    <bndbox>
      <xmin>181</xmin>
      <ymin>78</ymin>
      <xmax>207</xmax>
      <ymax>140</ymax>
    </bndbox>
  </object>
  <object>
    <name>person</name>
    <difficult>0</difficult>
    <bndbox>
      <xmin>470</xmin>
      <ymin>79</ymin>
      <xmax>478</xmax>
      <ymax>89</ymax>
    </bndbox>
  </object>
  <object>
    <name>car</name>
    <difficult>0</difficult>
    <bndbox>
      <xmin>0</xmin>
      <ymin>88</ymin>
      <xmax>43</xmax>
      <ymax>161</ymax>
    </bndbox>
  </object>
  <object>
    <name>car</name>
    <difficult>0</difficult>
    <bndbox>
      <xmin>101</xmin>
      <ymin>78</ymin>
      <xmax>147</xmax>
      <ymax>120</ymax>
    </bndbox>
  </object>
  <object>
    <name>car</name>
    <difficult>0</difficult>
    <bndbox>
      <xmin>283</xmin>
      <ymin>71</ymin>
      <xmax>298</xmax>
      <ymax>85</ymax>
    </bndbox>
  </object>
  <object>
    <name>car</name>
    <difficult>0</difficult>
    <bndbox>
      <xmin>336</xmin>
      <ymin>65</ymin>
      <xmax>346</xmax>
      <ymax>74</ymax>
    </bndbox>
  </object>
</annotation>
