<annotation>
  <path>dataset\images\train\000000373846.jpg</path><folder>JPEG</folder>
  <filename>000000373846.jpg</filename>
  <size>
    <width>640</width>
    <height>427</height>
    <depth>3</depth>
  </size>
  <object>
    <name>person</name>
    <difficult>0</difficult>
    <bndbox>
      <xmin>464</xmin>
      <ymin>231</ymin>
      <xmax>479</xmax>
      <ymax>270</ymax>
    </bndbox>
  </object>
  <object>
    <name>person</name>
    <difficult>0</difficult>
    <bndbox>
      <xmin>199</xmin>
      <ymin>321</ymin>
      <xmax>214</xmax>
      <ymax>393</ymax>
    </bndbox>
  </object>
  <object>
    <name>person</name>
    <difficult>0</difficult>
    <bndbox>
      <xmin>188</xmin>
      <ymin>254</ymin>
      <xmax>200</xmax>
      <ymax>300</ymax>
    </bndbox>
  </object>
  <object>
    <name>person</name>
    <difficult>0</difficult>
    <bndbox>
      <xmin>213</xmin>
      <ymin>326</ymin>
      <xmax>240</xmax>
      <ymax>394</ymax>
    </bndbox>
  </object>
</annotation>
