<annotation>
  <path>dataset\images\train\000000087616.jpg</path><folder>JPEG</folder>
  <filename>000000087616.jpg</filename>
  <size>
    <width>500</width>
    <height>333</height>
    <depth>3</depth>
  </size>
  <object>
    <name>person</name>
    <difficult>0</difficult>
    <bndbox>
      <xmin>161</xmin>
      <ymin>90</ymin>
      <xmax>252</xmax>
      <ymax>156</ymax>
    </bndbox>
  </object>
  <object>
    <name>person</name>
    <difficult>0</difficult>
    <bndbox>
      <xmin>269</xmin>
      <ymin>111</ymin>
      <xmax>393</xmax>
      <ymax>243</ymax>
    </bndbox>
  </object>
  <object>
    <name>person</name>
    <difficult>0</difficult>
    <bndbox>
      <xmin>277</xmin>
      <ymin>19</ymin>
      <xmax>500</xmax>
      <ymax>294</ymax>
    </bndbox>
  </object>
  <object>
    <name>person</name>
    <difficult>0</difficult>
    <bndbox>
      <xmin>360</xmin>
      <ymin>123</ymin>
      <xmax>371</xmax>
      <ymax>143</ymax>
    </bndbox>
  </object>
</annotation>
