<annotation>
  <path>dataset\images\train\000000004080.jpg</path><folder>JPEG</folder>
  <filename>000000004080.jpg</filename>
  <size>
    <width>458</width>
    <height>640</height>
    <depth>3</depth>
  </size>
  <object>
    <name>person</name>
    <difficult>0</difficult>
    <bndbox>
      <xmin>309</xmin>
      <ymin>162</ymin>
      <xmax>340</xmax>
      <ymax>240</ymax>
    </bndbox>
  </object>
  <object>
    <name>person</name>
    <difficult>0</difficult>
    <bndbox>
      <xmin>289</xmin>
      <ymin>420</ymin>
      <xmax>295</xmax>
      <ymax>434</ymax>
    </bndbox>
  </object>
  <object>
    <name>person</name>
    <difficult>0</difficult>
    <bndbox>
      <xmin>293</xmin>
      <ymin>417</ymin>
      <xmax>296</xmax>
      <ymax>425</ymax>
    </bndbox>
  </object>
  <object>
    <name>person</name>
    <difficult>0</difficult>
    <bndbox>
      <xmin>140</xmin>
      <ymin>136</ymin>
      <xmax>164</xmax>
      <ymax>218</ymax>
    </bndbox>
  </object>
  <object>
    <name>person</name>
    <difficult>0</difficult>
    <bndbox>
      <xmin>0</xmin>
      <ymin>174</ymin>
      <xmax>13</xmax>
      <ymax>243</ymax>
    </bndbox>
  </object>
</annotation>
