<annotation>
  <path>dataset\images\train\000000559778.jpg</path><folder>JPEG</folder>
  <filename>000000559778.jpg</filename>
  <size>
    <width>500</width>
    <height>375</height>
    <depth>3</depth>
  </size>
  <object>
    <name>dog</name>
    <difficult>0</difficult>
    <bndbox>
      <xmin>95</xmin>
      <ymin>87</ymin>
      <xmax>500</xmax>
      <ymax>294</ymax>
    </bndbox>
  </object>
  <object>
    <name>dog</name>
    <difficult>0</difficult>
    <bndbox>
      <xmin>250</xmin>
      <ymin>15</ymin>
      <xmax>360</xmax>
      <ymax>93</ymax>
    </bndbox>
  </object>
  <object>
    <name>person</name>
    <difficult>0</difficult>
    <bndbox>
      <xmin>427</xmin>
      <ymin>224</ymin>
      <xmax>500</xmax>
      <ymax>362</ymax>
    </bndbox>
  </object>
</annotation>
