<annotation>
  <path>dataset\images\train\000000567764.jpg</path><folder>JPEG</folder>
  <filename>000000567764.jpg</filename>
  <size>
    <width>640</width>
    <height>490</height>
    <depth>3</depth>
  </size>
  <object>
    <name>person</name>
    <difficult>0</difficult>
    <bndbox>
      <xmin>77</xmin>
      <ymin>96</ymin>
      <xmax>372</xmax>
      <ymax>483</ymax>
    </bndbox>
  </object>
  <object>
    <name>person</name>
    <difficult>0</difficult>
    <bndbox>
      <xmin>539</xmin>
      <ymin>22</ymin>
      <xmax>603</xmax>
      <ymax>251</ymax>
    </bndbox>
  </object>
  <object>
    <name>person</name>
    <difficult>0</difficult>
    <bndbox>
      <xmin>45</xmin>
      <ymin>18</ymin>
      <xmax>78</xmax>
      <ymax>40</ymax>
    </bndbox>
  </object>
  <object>
    <name>person</name>
    <difficult>0</difficult>
    <bndbox>
      <xmin>28</xmin>
      <ymin>19</ymin>
      <xmax>51</xmax>
      <ymax>42</ymax>
    </bndbox>
  </object>
  <object>
    <name>person</name>
    <difficult>0</difficult>
    <bndbox>
      <xmin>28</xmin>
      <ymin>3</ymin>
      <xmax>38</xmax>
      <ymax>17</ymax>
    </bndbox>
  </object>
  <object>
    <name>person</name>
    <difficult>0</difficult>
    <bndbox>
      <xmin>55</xmin>
      <ymin>0</ymin>
      <xmax>71</xmax>
      <ymax>22</ymax>
    </bndbox>
  </object>
  <object>
    <name>person</name>
    <difficult>0</difficult>
    <bndbox>
      <xmin>214</xmin>
      <ymin>0</ymin>
      <xmax>238</xmax>
      <ymax>59</ymax>
    </bndbox>
  </object>
  <object>
    <name>person</name>
    <difficult>0</difficult>
    <bndbox>
      <xmin>455</xmin>
      <ymin>10</ymin>
      <xmax>503</xmax>
      <ymax>131</ymax>
    </bndbox>
  </object>
</annotation>
