<annotation>
  <path>dataset\images\train\000000186821.jpg</path><folder>JPEG</folder>
  <filename>000000186821.jpg</filename>
  <size>
    <width>640</width>
    <height>425</height>
    <depth>3</depth>
  </size>
  <object>
    <name>car</name>
    <difficult>0</difficult>
    <bndbox>
      <xmin>24</xmin>
      <ymin>267</ymin>
      <xmax>130</xmax>
      <ymax>373</ymax>
    </bndbox>
  </object>
  <object>
    <name>person</name>
    <difficult>0</difficult>
    <bndbox>
      <xmin>438</xmin>
      <ymin>227</ymin>
      <xmax>481</xmax>
      <ymax>353</ymax>
    </bndbox>
  </object>
  <object>
    <name>person</name>
    <difficult>0</difficult>
    <bndbox>
      <xmin>478</xmin>
      <ymin>226</ymin>
      <xmax>518</xmax>
      <ymax>342</ymax>
    </bndbox>
  </object>
  <object>
    <name>person</name>
    <difficult>0</difficult>
    <bndbox>
      <xmin>549</xmin>
      <ymin>224</ymin>
      <xmax>598</xmax>
      <ymax>351</ymax>
    </bndbox>
  </object>
  <object>
    <name>person</name>
    <difficult>0</difficult>
    <bndbox>
      <xmin>538</xmin>
      <ymin>239</ymin>
      <xmax>552</xmax>
      <ymax>256</ymax>
    </bndbox>
  </object>
  <object>
    <name>person</name>
    <difficult>0</difficult>
    <bndbox>
      <xmin>611</xmin>
      <ymin>217</ymin>
      <xmax>640</xmax>
      <ymax>403</ymax>
    </bndbox>
  </object>
  <object>
    <name>person</name>
    <difficult>0</difficult>
    <bndbox>
      <xmin>601</xmin>
      <ymin>237</ymin>
      <xmax>623</xmax>
      <ymax>314</ymax>
    </bndbox>
  </object>
  <object>
    <name>person</name>
    <difficult>0</difficult>
    <bndbox>
      <xmin>528</xmin>
      <ymin>244</ymin>
      <xmax>557</xmax>
      <ymax>317</ymax>
    </bndbox>
  </object>
  <object>
    <name>person</name>
    <difficult>0</difficult>
    <bndbox>
      <xmin>582</xmin>
      <ymin>240</ymin>
      <xmax>603</xmax>
      <ymax>313</ymax>
    </bndbox>
  </object>
  <object>
    <name>person</name>
    <difficult>0</difficult>
    <bndbox>
      <xmin>498</xmin>
      <ymin>230</ymin>
      <xmax>527</xmax>
      <ymax>338</ymax>
    </bndbox>
  </object>
</annotation>
