<annotation>
  <path>dataset\images\train\000000216576.jpg</path><folder>JPEG</folder>
  <filename>000000216576.jpg</filename>
  <size>
    <width>640</width>
    <height>297</height>
    <depth>3</depth>
  </size>
  <object>
    <name>person</name>
    <difficult>0</difficult>
    <bndbox>
      <xmin>253</xmin>
      <ymin>82</ymin>
      <xmax>294</xmax>
      <ymax>221</ymax>
    </bndbox>
  </object>
  <object>
    <name>person</name>
    <difficult>0</difficult>
    <bndbox>
      <xmin>1</xmin>
      <ymin>73</ymin>
      <xmax>61</xmax>
      <ymax>249</ymax>
    </bndbox>
  </object>
  <object>
    <name>person</name>
    <difficult>0</difficult>
    <bndbox>
      <xmin>59</xmin>
      <ymin>79</ymin>
      <xmax>109</xmax>
      <ymax>238</ymax>
    </bndbox>
  </object>
  <object>
    <name>person</name>
    <difficult>0</difficult>
    <bndbox>
      <xmin>568</xmin>
      <ymin>87</ymin>
      <xmax>640</xmax>
      <ymax>267</ymax>
    </bndbox>
  </object>
  <object>
    <name>person</name>
    <difficult>0</difficult>
    <bndbox>
      <xmin>160</xmin>
      <ymin>97</ymin>
      <xmax>193</xmax>
      <ymax>225</ymax>
    </bndbox>
  </object>
  <object>
    <name>person</name>
    <difficult>0</difficult>
    <bndbox>
      <xmin>509</xmin>
      <ymin>81</ymin>
      <xmax>563</xmax>
      <ymax>253</ymax>
    </bndbox>
  </object>
  <object>
    <name>person</name>
    <difficult>0</difficult>
    <bndbox>
      <xmin>310</xmin>
      <ymin>93</ymin>
      <xmax>350</xmax>
      <ymax>227</ymax>
    </bndbox>
  </object>
  <object>
    <name>person</name>
    <difficult>0</difficult>
    <bndbox>
      <xmin>347</xmin>
      <ymin>73</ymin>
      <xmax>392</xmax>
      <ymax>225</ymax>
    </bndbox>
  </object>
  <object>
    <name>person</name>
    <difficult>0</difficult>
    <bndbox>
      <xmin>382</xmin>
      <ymin>101</ymin>
      <xmax>419</xmax>
      <ymax>230</ymax>
    </bndbox>
  </object>
  <object>
    <name>person</name>
    <difficult>0</difficult>
    <bndbox>
      <xmin>463</xmin>
      <ymin>81</ymin>
      <xmax>506</xmax>
      <ymax>245</ymax>
    </bndbox>
  </object>
  <object>
    <name>person</name>
    <difficult>0</difficult>
    <bndbox>
      <xmin>412</xmin>
      <ymin>84</ymin>
      <xmax>461</xmax>
      <ymax>236</ymax>
    </bndbox>
  </object>
  <object>
    <name>person</name>
    <difficult>0</difficult>
    <bndbox>
      <xmin>272</xmin>
      <ymin>88</ymin>
      <xmax>321</xmax>
      <ymax>224</ymax>
    </bndbox>
  </object>
  <object>
    <name>person</name>
    <difficult>0</difficult>
    <bndbox>
      <xmin>192</xmin>
      <ymin>108</ymin>
      <xmax>235</xmax>
      <ymax>223</ymax>
    </bndbox>
  </object>
  <object>
    <name>person</name>
    <difficult>0</difficult>
    <bndbox>
      <xmin>102</xmin>
      <ymin>81</ymin>
      <xmax>583</xmax>
      <ymax>234</ymax>
    </bndbox>
  </object>
</annotation>
