<annotation>
  <path>dataset\images\train\000000224508.jpg</path><folder>JPEG</folder>
  <filename>000000224508.jpg</filename>
  <size>
    <width>640</width>
    <height>428</height>
    <depth>3</depth>
  </size>
  <object>
    <name>person</name>
    <difficult>0</difficult>
    <bndbox>
      <xmin>211</xmin>
      <ymin>130</ymin>
      <xmax>255</xmax>
      <ymax>239</ymax>
    </bndbox>
  </object>
  <object>
    <name>person</name>
    <difficult>0</difficult>
    <bndbox>
      <xmin>438</xmin>
      <ymin>135</ymin>
      <xmax>490</xmax>
      <ymax>255</ymax>
    </bndbox>
  </object>
  <object>
    <name>person</name>
    <difficult>0</difficult>
    <bndbox>
      <xmin>287</xmin>
      <ymin>137</ymin>
      <xmax>341</xmax>
      <ymax>258</ymax>
    </bndbox>
  </object>
</annotation>
