<annotation>
  <path>dataset\images\train\000000432255.jpg</path><folder>JPEG</folder>
  <filename>000000432255.jpg</filename>
  <size>
    <width>480</width>
    <height>640</height>
    <depth>3</depth>
  </size>
  <object>
    <name>person</name>
    <difficult>0</difficult>
    <bndbox>
      <xmin>91</xmin>
      <ymin>136</ymin>
      <xmax>265</xmax>
      <ymax>601</ymax>
    </bndbox>
  </object>
  <object>
    <name>person</name>
    <difficult>0</difficult>
    <bndbox>
      <xmin>5</xmin>
      <ymin>223</ymin>
      <xmax>46</xmax>
      <ymax>296</ymax>
    </bndbox>
  </object>
  <object>
    <name>person</name>
    <difficult>0</difficult>
    <bndbox>
      <xmin>408</xmin>
      <ymin>254</ymin>
      <xmax>420</xmax>
      <ymax>283</ymax>
    </bndbox>
  </object>
  <object>
    <name>person</name>
    <difficult>0</difficult>
    <bndbox>
      <xmin>428</xmin>
      <ymin>251</ymin>
      <xmax>436</xmax>
      <ymax>284</ymax>
    </bndbox>
  </object>
  <object>
    <name>person</name>
    <difficult>0</difficult>
    <bndbox>
      <xmin>372</xmin>
      <ymin>252</ymin>
      <xmax>379</xmax>
      <ymax>272</ymax>
    </bndbox>
  </object>
  <object>
    <name>person</name>
    <difficult>0</difficult>
    <bndbox>
      <xmin>32</xmin>
      <ymin>238</ymin>
      <xmax>38</xmax>
      <ymax>248</ymax>
    </bndbox>
  </object>
  <object>
    <name>person</name>
    <difficult>0</difficult>
    <bndbox>
      <xmin>415</xmin>
      <ymin>274</ymin>
      <xmax>427</xmax>
      <ymax>283</ymax>
    </bndbox>
  </object>
</annotation>
