<annotation>
  <path>dataset\images\train\000000486451.jpg</path><folder>JPEG</folder>
  <filename>000000486451.jpg</filename>
  <size>
    <width>640</width>
    <height>361</height>
    <depth>3</depth>
  </size>
  <object>
    <name>person</name>
    <difficult>0</difficult>
    <bndbox>
      <xmin>116</xmin>
      <ymin>224</ymin>
      <xmax>130</xmax>
      <ymax>256</ymax>
    </bndbox>
  </object>
  <object>
    <name>person</name>
    <difficult>0</difficult>
    <bndbox>
      <xmin>288</xmin>
      <ymin>204</ymin>
      <xmax>306</xmax>
      <ymax>231</ymax>
    </bndbox>
  </object>
  <object>
    <name>person</name>
    <difficult>0</difficult>
    <bndbox>
      <xmin>480</xmin>
      <ymin>183</ymin>
      <xmax>512</xmax>
      <ymax>218</ymax>
    </bndbox>
  </object>
  <object>
    <name>person</name>
    <difficult>0</difficult>
    <bndbox>
      <xmin>527</xmin>
      <ymin>188</ymin>
      <xmax>556</xmax>
      <ymax>213</ymax>
    </bndbox>
  </object>
</annotation>
