<annotation>
  <path>dataset\images\train\000000358058.jpg</path><folder>JPEG</folder>
  <filename>000000358058.jpg</filename>
  <size>
    <width>429</width>
    <height>640</height>
    <depth>3</depth>
  </size>
  <object>
    <name>person</name>
    <difficult>0</difficult>
    <bndbox>
      <xmin>56</xmin>
      <ymin>104</ymin>
      <xmax>396</xmax>
      <ymax>640</ymax>
    </bndbox>
  </object>
  <object>
    <name>person</name>
    <difficult>0</difficult>
    <bndbox>
      <xmin>116</xmin>
      <ymin>119</ymin>
      <xmax>172</xmax>
      <ymax>222</ymax>
    </bndbox>
  </object>
  <object>
    <name>person</name>
    <difficult>0</difficult>
    <bndbox>
      <xmin>91</xmin>
      <ymin>199</ymin>
      <xmax>137</xmax>
      <ymax>245</ymax>
    </bndbox>
  </object>
  <object>
    <name>person</name>
    <difficult>0</difficult>
    <bndbox>
      <xmin>103</xmin>
      <ymin>153</ymin>
      <xmax>135</xmax>
      <ymax>201</ymax>
    </bndbox>
  </object>
  <object>
    <name>person</name>
    <difficult>0</difficult>
    <bndbox>
      <xmin>2</xmin>
      <ymin>126</ymin>
      <xmax>58</xmax>
      <ymax>356</ymax>
    </bndbox>
  </object>
</annotation>
