<annotation>
  <path>dataset\images\train\000000028127.jpg</path><folder>JPEG</folder>
  <filename>000000028127.jpg</filename>
  <size>
    <width>640</width>
    <height>640</height>
    <depth>3</depth>
  </size>
  <object>
    <name>person</name>
    <difficult>0</difficult>
    <bndbox>
      <xmin>64</xmin>
      <ymin>354</ymin>
      <xmax>162</xmax>
      <ymax>561</ymax>
    </bndbox>
  </object>
  <object>
    <name>person</name>
    <difficult>0</difficult>
    <bndbox>
      <xmin>479</xmin>
      <ymin>318</ymin>
      <xmax>575</xmax>
      <ymax>515</ymax>
    </bndbox>
  </object>
</annotation>
