<annotation>
  <path>dataset\images\train\000000233688.jpg</path><folder>JPEG</folder>
  <filename>000000233688.jpg</filename>
  <size>
    <width>427</width>
    <height>640</height>
    <depth>3</depth>
  </size>
  <object>
    <name>person</name>
    <difficult>0</difficult>
    <bndbox>
      <xmin>355</xmin>
      <ymin>267</ymin>
      <xmax>381</xmax>
      <ymax>339</ymax>
    </bndbox>
  </object>
  <object>
    <name>person</name>
    <difficult>0</difficult>
    <bndbox>
      <xmin>41</xmin>
      <ymin>97</ymin>
      <xmax>228</xmax>
      <ymax>307</ymax>
    </bndbox>
  </object>
  <object>
    <name>person</name>
    <difficult>0</difficult>
    <bndbox>
      <xmin>392</xmin>
      <ymin>263</ymin>
      <xmax>427</xmax>
      <ymax>335</ymax>
    </bndbox>
  </object>
</annotation>
