<annotation>
  <path>dataset\images\train\000000516372.jpg</path><folder>JPEG</folder>
  <filename>000000516372.jpg</filename>
  <size>
    <width>640</width>
    <height>480</height>
    <depth>3</depth>
  </size>
  <object>
    <name>car</name>
    <difficult>0</difficult>
    <bndbox>
      <xmin>337</xmin>
      <ymin>66</ymin>
      <xmax>419</xmax>
      <ymax>92</ymax>
    </bndbox>
  </object>
  <object>
    <name>car</name>
    <difficult>0</difficult>
    <bndbox>
      <xmin>389</xmin>
      <ymin>228</ymin>
      <xmax>638</xmax>
      <ymax>421</ymax>
    </bndbox>
  </object>
  <object>
    <name>car</name>
    <difficult>0</difficult>
    <bndbox>
      <xmin>346</xmin>
      <ymin>69</ymin>
      <xmax>418</xmax>
      <ymax>94</ymax>
    </bndbox>
  </object>
</annotation>
