<annotation>
  <path>dataset\images\train\000000315976.jpg</path><folder>JPEG</folder>
  <filename>000000315976.jpg</filename>
  <size>
    <width>612</width>
    <height>612</height>
    <depth>3</depth>
  </size>
  <object>
    <name>person</name>
    <difficult>0</difficult>
    <bndbox>
      <xmin>533</xmin>
      <ymin>323</ymin>
      <xmax>556</xmax>
      <ymax>396</ymax>
    </bndbox>
  </object>
  <object>
    <name>person</name>
    <difficult>0</difficult>
    <bndbox>
      <xmin>238</xmin>
      <ymin>322</ymin>
      <xmax>282</xmax>
      <ymax>377</ymax>
    </bndbox>
  </object>
  <object>
    <name>person</name>
    <difficult>0</difficult>
    <bndbox>
      <xmin>543</xmin>
      <ymin>326</ymin>
      <xmax>561</xmax>
      <ymax>389</ymax>
    </bndbox>
  </object>
  <object>
    <name>bicycle</name>
    <difficult>0</difficult>
    <bndbox>
      <xmin>424</xmin>
      <ymin>375</ymin>
      <xmax>472</xmax>
      <ymax>413</ymax>
    </bndbox>
  </object>
  <object>
    <name>person</name>
    <difficult>0</difficult>
    <bndbox>
      <xmin>451</xmin>
      <ymin>360</ymin>
      <xmax>467</xmax>
      <ymax>417</ymax>
    </bndbox>
  </object>
</annotation>
