<annotation>
  <path>dataset\images\train\000000322263.jpg</path><folder>JPEG</folder>
  <filename>000000322263.jpg</filename>
  <size>
    <width>479</width>
    <height>640</height>
    <depth>3</depth>
  </size>
  <object>
    <name>motorcycle</name>
    <difficult>0</difficult>
    <bndbox>
      <xmin>30</xmin>
      <ymin>14</ymin>
      <xmax>479</xmax>
      <ymax>569</ymax>
    </bndbox>
  </object>
  <object>
    <name>person</name>
    <difficult>0</difficult>
    <bndbox>
      <xmin>193</xmin>
      <ymin>0</ymin>
      <xmax>268</xmax>
      <ymax>138</ymax>
    </bndbox>
  </object>
  <object>
    <name>person</name>
    <difficult>0</difficult>
    <bndbox>
      <xmin>355</xmin>
      <ymin>4</ymin>
      <xmax>402</xmax>
      <ymax>59</ymax>
    </bndbox>
  </object>
  <object>
    <name>person</name>
    <difficult>0</difficult>
    <bndbox>
      <xmin>6</xmin>
      <ymin>1</ymin>
      <xmax>39</xmax>
      <ymax>53</ymax>
    </bndbox>
  </object>
  <object>
    <name>person</name>
    <difficult>0</difficult>
    <bndbox>
      <xmin>266</xmin>
      <ymin>0</ymin>
      <xmax>343</xmax>
      <ymax>91</ymax>
    </bndbox>
  </object>
  <object>
    <name>motorcycle</name>
    <difficult>0</difficult>
    <bndbox>
      <xmin>422</xmin>
      <ymin>40</ymin>
      <xmax>479</xmax>
      <ymax>136</ymax>
    </bndbox>
  </object>
  <object>
    <name>person</name>
    <difficult>0</difficult>
    <bndbox>
      <xmin>449</xmin>
      <ymin>0</ymin>
      <xmax>469</xmax>
      <ymax>15</ymax>
    </bndbox>
  </object>
</annotation>
