<annotation>
  <path>dataset\images\train\000000298931.jpg</path><folder>JPEG</folder>
  <filename>000000298931.jpg</filename>
  <size>
    <width>500</width>
    <height>333</height>
    <depth>3</depth>
  </size>
  <object>
    <name>person</name>
    <difficult>0</difficult>
    <bndbox>
      <xmin>0</xmin>
      <ymin>31</ymin>
      <xmax>235</xmax>
      <ymax>332</ymax>
    </bndbox>
  </object>
  <object>
    <name>person</name>
    <difficult>0</difficult>
    <bndbox>
      <xmin>208</xmin>
      <ymin>0</ymin>
      <xmax>500</xmax>
      <ymax>329</ymax>
    </bndbox>
  </object>
</annotation>
