<annotation>
  <path>dataset\images\train\000000326354.jpg</path><folder>JPEG</folder>
  <filename>000000326354.jpg</filename>
  <size>
    <width>500</width>
    <height>333</height>
    <depth>3</depth>
  </size>
  <object>
    <name>person</name>
    <difficult>0</difficult>
    <bndbox>
      <xmin>235</xmin>
      <ymin>13</ymin>
      <xmax>441</xmax>
      <ymax>266</ymax>
    </bndbox>
  </object>
  <object>
    <name>person</name>
    <difficult>0</difficult>
    <bndbox>
      <xmin>264</xmin>
      <ymin>104</ymin>
      <xmax>286</xmax>
      <ymax>183</ymax>
    </bndbox>
  </object>
  <object>
    <name>person</name>
    <difficult>0</difficult>
    <bndbox>
      <xmin>66</xmin>
      <ymin>109</ymin>
      <xmax>98</xmax>
      <ymax>185</ymax>
    </bndbox>
  </object>
  <object>
    <name>person</name>
    <difficult>0</difficult>
    <bndbox>
      <xmin>99</xmin>
      <ymin>106</ymin>
      <xmax>132</xmax>
      <ymax>201</ymax>
    </bndbox>
  </object>
  <object>
    <name>person</name>
    <difficult>0</difficult>
    <bndbox>
      <xmin>229</xmin>
      <ymin>113</ymin>
      <xmax>250</xmax>
      <ymax>184</ymax>
    </bndbox>
  </object>
  <object>
    <name>person</name>
    <difficult>0</difficult>
    <bndbox>
      <xmin>438</xmin>
      <ymin>98</ymin>
      <xmax>489</xmax>
      <ymax>199</ymax>
    </bndbox>
  </object>
  <object>
    <name>person</name>
    <difficult>0</difficult>
    <bndbox>
      <xmin>2</xmin>
      <ymin>144</ymin>
      <xmax>25</xmax>
      <ymax>189</ymax>
    </bndbox>
  </object>
  <object>
    <name>person</name>
    <difficult>0</difficult>
    <bndbox>
      <xmin>72</xmin>
      <ymin>55</ymin>
      <xmax>215</xmax>
      <ymax>289</ymax>
    </bndbox>
  </object>
  <object>
    <name>car</name>
    <difficult>0</difficult>
    <bndbox>
      <xmin>377</xmin>
      <ymin>140</ymin>
      <xmax>406</xmax>
      <ymax>154</ymax>
    </bndbox>
  </object>
  <object>
    <name>person</name>
    <difficult>0</difficult>
    <bndbox>
      <xmin>283</xmin>
      <ymin>143</ymin>
      <xmax>293</xmax>
      <ymax>184</ymax>
    </bndbox>
  </object>
  <object>
    <name>person</name>
    <difficult>0</difficult>
    <bndbox>
      <xmin>39</xmin>
      <ymin>111</ymin>
      <xmax>64</xmax>
      <ymax>186</ymax>
    </bndbox>
  </object>
</annotation>
