<annotation>
  <path>dataset\images\train\000000399790.jpg</path><folder>JPEG</folder>
  <filename>000000399790.jpg</filename>
  <size>
    <width>640</width>
    <height>428</height>
    <depth>3</depth>
  </size>
  <object>
    <name>person</name>
    <difficult>0</difficult>
    <bndbox>
      <xmin>261</xmin>
      <ymin>186</ymin>
      <xmax>427</xmax>
      <ymax>335</ymax>
    </bndbox>
  </object>
  <object>
    <name>person</name>
    <difficult>0</difficult>
    <bndbox>
      <xmin>426</xmin>
      <ymin>96</ymin>
      <xmax>467</xmax>
      <ymax>195</ymax>
    </bndbox>
  </object>
  <object>
    <name>person</name>
    <difficult>0</difficult>
    <bndbox>
      <xmin>148</xmin>
      <ymin>2</ymin>
      <xmax>182</xmax>
      <ymax>40</ymax>
    </bndbox>
  </object>
  <object>
    <name>person</name>
    <difficult>0</difficult>
    <bndbox>
      <xmin>53</xmin>
      <ymin>0</ymin>
      <xmax>91</xmax>
      <ymax>40</ymax>
    </bndbox>
  </object>
  <object>
    <name>person</name>
    <difficult>0</difficult>
    <bndbox>
      <xmin>12</xmin>
      <ymin>0</ymin>
      <xmax>60</xmax>
      <ymax>41</ymax>
    </bndbox>
  </object>
</annotation>
