<annotation>
  <path>dataset\images\train\000000200838.jpg</path><folder>JPEG</folder>
  <filename>000000200838.jpg</filename>
  <size>
    <width>640</width>
    <height>443</height>
    <depth>3</depth>
  </size>
  <object>
    <name>person</name>
    <difficult>0</difficult>
    <bndbox>
      <xmin>469</xmin>
      <ymin>171</ymin>
      <xmax>484</xmax>
      <ymax>219</ymax>
    </bndbox>
  </object>
  <object>
    <name>person</name>
    <difficult>0</difficult>
    <bndbox>
      <xmin>458</xmin>
      <ymin>174</ymin>
      <xmax>468</xmax>
      <ymax>216</ymax>
    </bndbox>
  </object>
  <object>
    <name>person</name>
    <difficult>0</difficult>
    <bndbox>
      <xmin>445</xmin>
      <ymin>173</ymin>
      <xmax>457</xmax>
      <ymax>209</ymax>
    </bndbox>
  </object>
</annotation>
