<annotation>
  <path>dataset\images\train\000000383205.jpg</path><folder>JPEG</folder>
  <filename>000000383205.jpg</filename>
  <size>
    <width>640</width>
    <height>429</height>
    <depth>3</depth>
  </size>
  <object>
    <name>car</name>
    <difficult>0</difficult>
    <bndbox>
      <xmin>338</xmin>
      <ymin>145</ymin>
      <xmax>408</xmax>
      <ymax>188</ymax>
    </bndbox>
  </object>
  <object>
    <name>car</name>
    <difficult>0</difficult>
    <bndbox>
      <xmin>343</xmin>
      <ymin>150</ymin>
      <xmax>367</xmax>
      <ymax>169</ymax>
    </bndbox>
  </object>
  <object>
    <name>car</name>
    <difficult>0</difficult>
    <bndbox>
      <xmin>594</xmin>
      <ymin>152</ymin>
      <xmax>640</xmax>
      <ymax>179</ymax>
    </bndbox>
  </object>
</annotation>
