<annotation>
  <path>dataset\images\train\000000504108.jpg</path><folder>JPEG</folder>
  <filename>000000504108.jpg</filename>
  <size>
    <width>640</width>
    <height>480</height>
    <depth>3</depth>
  </size>
  <object>
    <name>person</name>
    <difficult>0</difficult>
    <bndbox>
      <xmin>129</xmin>
      <ymin>32</ymin>
      <xmax>379</xmax>
      <ymax>474</ymax>
    </bndbox>
  </object>
  <object>
    <name>person</name>
    <difficult>0</difficult>
    <bndbox>
      <xmin>1</xmin>
      <ymin>129</ymin>
      <xmax>82</xmax>
      <ymax>345</ymax>
    </bndbox>
  </object>
  <object>
    <name>person</name>
    <difficult>0</difficult>
    <bndbox>
      <xmin>554</xmin>
      <ymin>254</ymin>
      <xmax>640</xmax>
      <ymax>368</ymax>
    </bndbox>
  </object>
</annotation>
