<annotation>
  <path>dataset\images\train\000000509009.jpg</path><folder>JPEG</folder>
  <filename>000000509009.jpg</filename>
  <size>
    <width>480</width>
    <height>640</height>
    <depth>3</depth>
  </size>
  <object>
    <name>dog</name>
    <difficult>0</difficult>
    <bndbox>
      <xmin>168</xmin>
      <ymin>330</ymin>
      <xmax>248</xmax>
      <ymax>384</ymax>
    </bndbox>
  </object>
  <object>
    <name>person</name>
    <difficult>0</difficult>
    <bndbox>
      <xmin>118</xmin>
      <ymin>121</ymin>
      <xmax>454</xmax>
      <ymax>640</ymax>
    </bndbox>
  </object>
</annotation>
