<annotation>
  <path>dataset\images\train\000000163828.jpg</path><folder>JPEG</folder>
  <filename>000000163828.jpg</filename>
  <size>
    <width>640</width>
    <height>512</height>
    <depth>3</depth>
  </size>
  <object>
    <name>person</name>
    <difficult>0</difficult>
    <bndbox>
      <xmin>36</xmin>
      <ymin>205</ymin>
      <xmax>209</xmax>
      <ymax>512</ymax>
    </bndbox>
  </object>
  <object>
    <name>person</name>
    <difficult>0</difficult>
    <bndbox>
      <xmin>452</xmin>
      <ymin>72</ymin>
      <xmax>586</xmax>
      <ymax>358</ymax>
    </bndbox>
  </object>
  <object>
    <name>person</name>
    <difficult>0</difficult>
    <bndbox>
      <xmin>368</xmin>
      <ymin>215</ymin>
      <xmax>511</xmax>
      <ymax>360</ymax>
    </bndbox>
  </object>
  <object>
    <name>person</name>
    <difficult>0</difficult>
    <bndbox>
      <xmin>451</xmin>
      <ymin>103</ymin>
      <xmax>527</xmax>
      <ymax>238</ymax>
    </bndbox>
  </object>
  <object>
    <name>person</name>
    <difficult>0</difficult>
    <bndbox>
      <xmin>380</xmin>
      <ymin>109</ymin>
      <xmax>526</xmax>
      <ymax>413</ymax>
    </bndbox>
  </object>
</annotation>
