<annotation>
  <path>dataset\images\train\000000555475.jpg</path><folder>JPEG</folder>
  <filename>000000555475.jpg</filename>
  <size>
    <width>640</width>
    <height>480</height>
    <depth>3</depth>
  </size>
  <object>
    <name>car</name>
    <difficult>0</difficult>
    <bndbox>
      <xmin>0</xmin>
      <ymin>231</ymin>
      <xmax>227</xmax>
      <ymax>479</ymax>
    </bndbox>
  </object>
  <object>
    <name>car</name>
    <difficult>0</difficult>
    <bndbox>
      <xmin>503</xmin>
      <ymin>313</ymin>
      <xmax>640</xmax>
      <ymax>465</ymax>
    </bndbox>
  </object>
  <object>
    <name>car</name>
    <difficult>0</difficult>
    <bndbox>
      <xmin>504</xmin>
      <ymin>256</ymin>
      <xmax>640</xmax>
      <ymax>332</ymax>
    </bndbox>
  </object>
  <object>
    <name>car</name>
    <difficult>0</difficult>
    <bndbox>
      <xmin>109</xmin>
      <ymin>219</ymin>
      <xmax>164</xmax>
      <ymax>232</ymax>
    </bndbox>
  </object>
  <object>
    <name>car</name>
    <difficult>0</difficult>
    <bndbox>
      <xmin>158</xmin>
      <ymin>223</ymin>
      <xmax>185</xmax>
      <ymax>235</ymax>
    </bndbox>
  </object>
  <object>
    <name>motorcycle</name>
    <difficult>0</difficult>
    <bndbox>
      <xmin>251</xmin>
      <ymin>270</ymin>
      <xmax>378</xmax>
      <ymax>369</ymax>
    </bndbox>
  </object>
  <object>
    <name>person</name>
    <difficult>0</difficult>
    <bndbox>
      <xmin>264</xmin>
      <ymin>230</ymin>
      <xmax>346</xmax>
      <ymax>365</ymax>
    </bndbox>
  </object>
  <object>
    <name>person</name>
    <difficult>0</difficult>
    <bndbox>
      <xmin>557</xmin>
      <ymin>211</ymin>
      <xmax>575</xmax>
      <ymax>270</ymax>
    </bndbox>
  </object>
  <object>
    <name>person</name>
    <difficult>0</difficult>
    <bndbox>
      <xmin>563</xmin>
      <ymin>206</ymin>
      <xmax>571</xmax>
      <ymax>221</ymax>
    </bndbox>
  </object>
  <object>
    <name>person</name>
    <difficult>0</difficult>
    <bndbox>
      <xmin>490</xmin>
      <ymin>211</ymin>
      <xmax>496</xmax>
      <ymax>224</ymax>
    </bndbox>
  </object>
  <object>
    <name>person</name>
    <difficult>0</difficult>
    <bndbox>
      <xmin>478</xmin>
      <ymin>208</ymin>
      <xmax>485</xmax>
      <ymax>229</ymax>
    </bndbox>
  </object>
  <object>
    <name>person</name>
    <difficult>0</difficult>
    <bndbox>
      <xmin>471</xmin>
      <ymin>208</ymin>
      <xmax>478</xmax>
      <ymax>230</ymax>
    </bndbox>
  </object>
  <object>
    <name>person</name>
    <difficult>0</difficult>
    <bndbox>
      <xmin>453</xmin>
      <ymin>216</ymin>
      <xmax>462</xmax>
      <ymax>230</ymax>
    </bndbox>
  </object>
  <object>
    <name>person</name>
    <difficult>0</difficult>
    <bndbox>
      <xmin>439</xmin>
      <ymin>216</ymin>
      <xmax>446</xmax>
      <ymax>225</ymax>
    </bndbox>
  </object>
  <object>
    <name>person</name>
    <difficult>0</difficult>
    <bndbox>
      <xmin>532</xmin>
      <ymin>210</ymin>
      <xmax>558</xmax>
      <ymax>270</ymax>
    </bndbox>
  </object>
  <object>
    <name>person</name>
    <difficult>0</difficult>
    <bndbox>
      <xmin>603</xmin>
      <ymin>211</ymin>
      <xmax>611</xmax>
      <ymax>223</ymax>
    </bndbox>
  </object>
  <object>
    <name>person</name>
    <difficult>0</difficult>
    <bndbox>
      <xmin>502</xmin>
      <ymin>215</ymin>
      <xmax>507</xmax>
      <ymax>224</ymax>
    </bndbox>
  </object>
  <object>
    <name>car</name>
    <difficult>0</difficult>
    <bndbox>
      <xmin>308</xmin>
      <ymin>454</ymin>
      <xmax>628</xmax>
      <ymax>480</ymax>
    </bndbox>
  </object>
</annotation>
