<annotation>
  <path>dataset\images\train\000000049763.jpg</path><folder>JPEG</folder>
  <filename>000000049763.jpg</filename>
  <size>
    <width>500</width>
    <height>396</height>
    <depth>3</depth>
  </size>
  <object>
    <name>person</name>
    <difficult>0</difficult>
    <bndbox>
      <xmin>194</xmin>
      <ymin>210</ymin>
      <xmax>254</xmax>
      <ymax>325</ymax>
    </bndbox>
  </object>
  <object>
    <name>person</name>
    <difficult>0</difficult>
    <bndbox>
      <xmin>155</xmin>
      <ymin>223</ymin>
      <xmax>215</xmax>
      <ymax>327</ymax>
    </bndbox>
  </object>
  <object>
    <name>person</name>
    <difficult>0</difficult>
    <bndbox>
      <xmin>235</xmin>
      <ymin>234</ymin>
      <xmax>257</xmax>
      <ymax>291</ymax>
    </bndbox>
  </object>
</annotation>
