<annotation>
  <path>dataset\images\train\000000477435.jpg</path><folder>JPEG</folder>
  <filename>000000477435.jpg</filename>
  <size>
    <width>480</width>
    <height>640</height>
    <depth>3</depth>
  </size>
  <object>
    <name>bicycle</name>
    <difficult>0</difficult>
    <bndbox>
      <xmin>467</xmin>
      <ymin>417</ymin>
      <xmax>480</xmax>
      <ymax>436</ymax>
    </bndbox>
  </object>
  <object>
    <name>bicycle</name>
    <difficult>0</difficult>
    <bndbox>
      <xmin>325</xmin>
      <ymin>570</ymin>
      <xmax>359</xmax>
      <ymax>585</ymax>
    </bndbox>
  </object>
  <object>
    <name>bicycle</name>
    <difficult>0</difficult>
    <bndbox>
      <xmin>425</xmin>
      <ymin>405</ymin>
      <xmax>449</xmax>
      <ymax>435</ymax>
    </bndbox>
  </object>
  <object>
    <name>person</name>
    <difficult>0</difficult>
    <bndbox>
      <xmin>418</xmin>
      <ymin>386</ymin>
      <xmax>443</xmax>
      <ymax>435</ymax>
    </bndbox>
  </object>
  <object>
    <name>person</name>
    <difficult>0</difficult>
    <bndbox>
      <xmin>392</xmin>
      <ymin>398</ymin>
      <xmax>409</xmax>
      <ymax>427</ymax>
    </bndbox>
  </object>
</annotation>
